x_4357_make_mermaid_x/__init__.py
x_4357_make_mermaid_x/__init__.pyi
x_4357_make_mermaid_x/py.typed
x_4357_make_mermaid_x/x_cls_make_mermaid_x.py
x_4357_make_mermaid_x/x_cls_make_mermaid_x.pyi
x_4357_make_mermaid_x-0.20.17.dist-info/METADATA
x_4357_make_mermaid_x-0.20.17.dist-info/WHEEL
x_4357_make_mermaid_x-0.20.17.dist-info/top_level.txt
x_4357_make_mermaid_x-0.20.17.dist-info/RECORD
