Metadata-Version: 2.4
Name: x_4357_make_mermaid_x
Version: 0.20.17
Summary: Mermaid diagram builder.
Author-email: "RRGM (Software Tech Lead, Primus Pilus Night Watch AI Corp.)" <foo@bar.com>
Requires-Python: >=3.8
